LICENCE
README.md
setup.py
my_iqoptionapi/__init__.py
my_iqoptionapi/api.py
my_iqoptionapi/constants.py
my_iqoptionapi/country_id.py
my_iqoptionapi/expiration.py
my_iqoptionapi/global_value.py
my_iqoptionapi/stable_api.py
my_iqoptionapi/version_control.py
my_iqoptionapi.egg-info/PKG-INFO
my_iqoptionapi.egg-info/SOURCES.txt
my_iqoptionapi.egg-info/dependency_links.txt
my_iqoptionapi.egg-info/not-zip-safe
my_iqoptionapi.egg-info/requires.txt
my_iqoptionapi.egg-info/top_level.txt
my_iqoptionapi/http/__init__.py
my_iqoptionapi/http/appinit.py
my_iqoptionapi/http/auth.py
my_iqoptionapi/http/billing.py
my_iqoptionapi/http/buyback.py
my_iqoptionapi/http/changebalance.py
my_iqoptionapi/http/events.py
my_iqoptionapi/http/getprofile.py
my_iqoptionapi/http/getregdata.py
my_iqoptionapi/http/login.py
my_iqoptionapi/http/login2fa.py
my_iqoptionapi/http/loginv2.py
my_iqoptionapi/http/logout.py
my_iqoptionapi/http/profile.py
my_iqoptionapi/http/register.py
my_iqoptionapi/http/resource.py
my_iqoptionapi/http/send_sms.py
my_iqoptionapi/http/token.py
my_iqoptionapi/http/verify.py
my_iqoptionapi/ws/__init__.py
my_iqoptionapi/ws/client.py
my_iqoptionapi/ws/chanels/__init__.py
my_iqoptionapi/ws/chanels/api_game_betinfo.py
my_iqoptionapi/ws/chanels/api_game_getoptions.py
my_iqoptionapi/ws/chanels/base.py
my_iqoptionapi/ws/chanels/buy_place_order_temp.py
my_iqoptionapi/ws/chanels/buyback.py
my_iqoptionapi/ws/chanels/buyv2.py
my_iqoptionapi/ws/chanels/buyv3.py
my_iqoptionapi/ws/chanels/cancel_order.py
my_iqoptionapi/ws/chanels/candles.py
my_iqoptionapi/ws/chanels/change_auto_margin_call.py
my_iqoptionapi/ws/chanels/change_tpsl.py
my_iqoptionapi/ws/chanels/changebalance.py
my_iqoptionapi/ws/chanels/close_position.py
my_iqoptionapi/ws/chanels/digital_option.py
my_iqoptionapi/ws/chanels/get_available_leverages.py
my_iqoptionapi/ws/chanels/get_balances.py
my_iqoptionapi/ws/chanels/get_deferred_orders.py
my_iqoptionapi/ws/chanels/get_financial_information.py
my_iqoptionapi/ws/chanels/get_order.py
my_iqoptionapi/ws/chanels/get_overnight_fee.py
my_iqoptionapi/ws/chanels/get_positions.py
my_iqoptionapi/ws/chanels/heartbeat.py
my_iqoptionapi/ws/chanels/instruments.py
my_iqoptionapi/ws/chanels/leaderboard.py
