Metadata-Version: 2.1
Name: my-iqoptionapi
Version: 7.1.2
Summary: Best IQ Option API for python
Home-page: https://github.com/zskull-py/iqoptionapi
Author: zSkull.py
License: UNKNOWN
Keywords: iqoption
Platform: UNKNOWN
License-File: LICENCE
